gen_surv/__init__.py
gen_surv/__main__.py
gen_surv/aft.py
gen_surv/bivariate.py
gen_surv/censoring.py
gen_surv/cli.py
gen_surv/cmm.py
gen_surv/cphm.py
gen_surv/interface.py
gen_surv/tdcm.py
gen_surv/thmm.py
gen_surv/validate.py
gen_surv-1.0.8.dist-info/LICENCE
gen_surv-1.0.8.dist-info/METADATA
gen_surv-1.0.8.dist-info/WHEEL
gen_surv-1.0.8.dist-info/RECORD
