Metadata-Version: 2.3
Name: gen_surv
Version: 1.0.8
Summary: A Python package for simulating survival data, inspired by the R package genSurv
Home-page: https://github.com/DiogoRibeiro7/genSurvPy
License: MIT
Author: Diogo Ribeiro
Author-email: diogo.debastos.ribeiro@gmail.com
Requires-Python: >=3.9,<4.0
Classifier: License :: OSI Approved :: MIT License
Classifier: Programming Language :: Python :: 3
Classifier: Programming Language :: Python :: 3.9
Classifier: Programming Language :: Python :: 3.10
Classifier: Programming Language :: Python :: 3.11
Classifier: Programming Language :: Python :: 3.12
Classifier: Programming Language :: Python :: 3.13
Requires-Dist: invoke (>=2.2.0,<3.0.0)
Requires-Dist: numpy (>=1.26,<2.0)
Requires-Dist: pandas (>=2.2.3,<3.0.0)
Requires-Dist: pytest-cov (>=6.1.1,<7.0.0)
Requires-Dist: tomli (>=2.2.1,<3.0.0)
Requires-Dist: typer (>=0.12.3,<0.13.0)
Project-URL: Documentation, https://gensurvpy.readthedocs.io/en/stable/
Project-URL: Repository, https://github.com/DiogoRibeiro7/genSurvPy
